smolgp/__init__.py
smolgp/gp.py
smolgp/helpers.py
smolgp/kernels/__init__.py
smolgp/kernels/base.py
smolgp/kernels/integrated.py
smolgp/solvers/__init__.py
smolgp/solvers/kalman.py
smolgp/solvers/rts.py
smolgp/solvers/solver.py
smolgp/solvers/integrated/__init__.py
smolgp/solvers/integrated/kalman.py
smolgp/solvers/integrated/rts.py
smolgp/solvers/integrated/solver.py
smolgp/solvers/integrated/parallel/__init__.py
smolgp/solvers/integrated/parallel/kalman.py
smolgp/solvers/integrated/parallel/rts.py
smolgp/solvers/integrated/parallel/solver.py
smolgp/solvers/parallel/__init__.py
smolgp/solvers/parallel/kalman.py
smolgp/solvers/parallel/rts.py
smolgp/solvers/parallel/solver.py
smolgp-0.1.0.dist-info/METADATA
smolgp-0.1.0.dist-info/WHEEL
smolgp-0.1.0.dist-info/licenses/LICENSE
smolgp-0.1.0.dist-info/RECORD
