Metadata-Version: 2.4
Name: smolgp
Version: 0.1.0
Summary: Gaussian Process State Space Models in Python/JAX
Project-URL: Homepage, https://github.com/smolgp-dev/smolgp
Project-URL: Issues, https://github.com/smolgp-dev/smolgp/issues
Author-email: Ryan Rubenzahl <rrubenzahl@gmail.com>, Soichiro Hattori <soichiro.hattori@gmail.com>
License: MIT
License-File: LICENSE
Classifier: Development Status :: 4 - Beta
Classifier: Intended Audience :: Developers
Classifier: Intended Audience :: Science/Research
Classifier: License :: OSI Approved :: MIT License
Classifier: Operating System :: OS Independent
Classifier: Programming Language :: Python
Classifier: Programming Language :: Python :: 3
Requires-Python: >=3.10
Requires-Dist: equinox>=0.13.1
Requires-Dist: jax>=0.6.2
Requires-Dist: tinygp>=0.3.0
Provides-Extra: cuda12
Requires-Dist: jax[cuda12]; extra == 'cuda12'
Provides-Extra: cuda13
Requires-Dist: jax[cuda13]; extra == 'cuda13'
